cvlab_keras/__init__.py
cvlab_keras/batch_loader.py
cvlab_keras/imagenet.py
cvlab_keras/model_io.py
cvlab_keras/model_operations.py
cvlab_keras/model_utils.py
cvlab_keras/shared.py
cvlab_keras/visualisation.py
cvlab_keras/images/mnist/0.png
cvlab_keras/images/mnist/1.png
cvlab_keras/images/mnist/2.png
cvlab_keras/images/mnist/3.png
cvlab_keras/images/mnist/4.png
cvlab_keras/images/mnist/5.png
cvlab_keras/images/mnist/6.png
cvlab_keras/images/mnist/7.png
cvlab_keras/images/mnist/8.png
cvlab_keras/images/mnist/9.png
cvlab_keras/models/MNIST_model.h5
cvlab_keras/samples/ImageNet.cvlab
cvlab_keras/samples/MNIST_Testing.cvlab
cvlab_keras/samples/MNIST_Training.cvlab
cvlab_keras-1.1.dist-info/LICENSE
cvlab_keras-1.1.dist-info/METADATA
cvlab_keras-1.1.dist-info/WHEEL
cvlab_keras-1.1.dist-info/top_level.txt
cvlab_keras-1.1.dist-info/RECORD
