Metadata-Version: 2.1
Name: cvlab-keras
Version: 1.1
Summary: # Machine learning toolkit for CV-Lab
Home-page: https://github.com/cvlab-keras/cvlab_keras
Author: Karolina Baryłka, Katarzyna Kaczorowska, Filip Chodziutko
License: AGPL-3.0+
Platform: UNKNOWN
Requires-Python: >=3.5
Requires-Dist: cvlab (>=1.3.0rc1)
Requires-Dist: tensorflow (>=2.3)
